tiscontrolv2/__init__.py
tiscontrolv2/tiscontrolv2.py
tiscontrolv2-0.0.15.dist-info/licenses/LICENSE
tiscontrolv2-0.0.15.dist-info/METADATA
tiscontrolv2-0.0.15.dist-info/WHEEL
tiscontrolv2-0.0.15.dist-info/top_level.txt
tiscontrolv2-0.0.15.dist-info/RECORD
