Metadata-Version: 2.4
Name: tiscontrolv2
Version: 0.0.15
Summary: Python library to provide a reliable communication link with TIS  Products
Home-page: https://github.com/tiscontrol/tiscontrolv2
Author: tiscontrol
Author-email: gopaltis93@gmail.com
License: MIT
Keywords: tiscontrolv2,tiscontrol
License-File: LICENSE
Dynamic: author
Dynamic: author-email
Dynamic: description
Dynamic: description-content-type
Dynamic: home-page
Dynamic: keywords
Dynamic: license
Dynamic: license-file
Dynamic: summary
